bandlab_master/__init__.py
bandlab_master/__main__.py
bandlab_master-1.3.0.dist-info/LICENSE
bandlab_master-1.3.0.dist-info/METADATA
bandlab_master-1.3.0.dist-info/WHEEL
bandlab_master-1.3.0.dist-info/entry_points.txt
bandlab_master-1.3.0.dist-info/top_level.txt
bandlab_master-1.3.0.dist-info/RECORD
