Metadata-Version: 2.1
Name: bandlab-master
Version: 1.3.0
Summary: Master a song with BandLab
Home-page: https://github.com/zmarffy/bandlab-master
Author: Zeke Marffy
Author-email: zmarffy@yahoo.com
License: MIT
Platform: UNKNOWN
Requires-Python: >=3.6
Requires-Dist: selenium
Requires-Dist: webdriver-extended (>=1.1)
